rle.pyd
rdpy/__init__.py
rdpy/core/const.py
rdpy/core/error.py
rdpy/core/filetimes.py
rdpy/core/layer.py
rdpy/core/log.py
rdpy/core/rss.py
rdpy/core/scancode.py
rdpy/core/type.py
rdpy/core/__init__.py
rdpy/protocol/__init__.py
rdpy/protocol/rdp/lic.py
rdpy/protocol/rdp/rdp.py
rdpy/protocol/rdp/sec.py
rdpy/protocol/rdp/tpkt.py
rdpy/protocol/rdp/x224.py
rdpy/protocol/rdp/__init__.py
rdpy/protocol/rdp/nla/cssp.py
rdpy/protocol/rdp/nla/ntlm.py
rdpy/protocol/rdp/nla/sspi.py
rdpy/protocol/rdp/nla/__init__.py
rdpy/protocol/rdp/pdu/caps.py
rdpy/protocol/rdp/pdu/data.py
rdpy/protocol/rdp/pdu/layer.py
rdpy/protocol/rdp/pdu/order.py
rdpy/protocol/rdp/pdu/__init__.py
rdpy/protocol/rdp/t125/ber.py
rdpy/protocol/rdp/t125/gcc.py
rdpy/protocol/rdp/t125/mcs.py
rdpy/protocol/rdp/t125/per.py
rdpy/protocol/rdp/t125/__init__.py
rdpy/protocol/rfb/rfb.py
rdpy/protocol/rfb/__init__.py
rdpy/security/pyDes.py
rdpy/security/rc4.py
rdpy/security/rsa_wrapper.py
rdpy/security/x509.py
rdpy/security/__init__.py
rdpy/ui/qt4.py
rdpy/ui/view.py
rdpy/ui/__init__.py
rdpy-1.3.2.data/scripts/rdpy-rdpclient.py
rdpy-1.3.2.data/scripts/rdpy-rdphoneypot.py
rdpy-1.3.2.data/scripts/rdpy-rdpmitm.py
rdpy-1.3.2.data/scripts/rdpy-rdpscreenshot.py
rdpy-1.3.2.data/scripts/rdpy-rssplayer.py
rdpy-1.3.2.data/scripts/rdpy-vncclient.py
rdpy-1.3.2.data/scripts/rdpy-vncscreenshot.py
rdpy-1.3.2.dist-info/DESCRIPTION.rst
rdpy-1.3.2.dist-info/METADATA
rdpy-1.3.2.dist-info/metadata.json
rdpy-1.3.2.dist-info/RECORD
rdpy-1.3.2.dist-info/top_level.txt
rdpy-1.3.2.dist-info/WHEEL
