Metadata-Version: 2.0
Name: rdpy
Version: 1.3.2
Summary: Remote Desktop Protocol in Python
Home-page: https://github.com/citronneur/rdpy
Author: Sylvain Peyrefitte
Author-email: citronneur@gmail.com
License: UNKNOWN
Platform: UNKNOWN
Requires-Dist: twisted
Requires-Dist: pyopenssl
Requires-Dist: service-identity
Requires-Dist: qt4reactor
Requires-Dist: rsa
Requires-Dist: pyasn1
